xport/__about__.py
xport/__init__.py
xport/__main__.py
xport/cli.py
xport/cport.py
xport/sas7bdat.py
xport/v56.py
xport/v89.py
xport-3.6.1.dist-info/LICENSE.txt
xport-3.6.1.dist-info/METADATA
xport-3.6.1.dist-info/WHEEL
xport-3.6.1.dist-info/entry_points.txt
xport-3.6.1.dist-info/top_level.txt
xport-3.6.1.dist-info/RECORD
