Metadata-Version: 2.1
Name: xport
Version: 3.6.1
Summary: SAS XPORT file reader
Home-page: https://github.com/selik/xport
Author: Michael Selik
Author-email: michael.selik@gmail.com
License: MIT
Keywords: sas,xport,xpt,cport,sas7bdat
Platform: any
Classifier: Development Status :: 4 - Beta
Classifier: Topic :: Text Processing
Classifier: Topic :: Utilities
Classifier: License :: OSI Approved :: MIT License
Classifier: Intended Audience :: Developers
Classifier: Operating System :: OS Independent
Classifier: Programming Language :: Python
Classifier: Programming Language :: Python :: 3 :: Only
Classifier: Programming Language :: Python :: 3.7
Classifier: Programming Language :: Python :: 3.8
Classifier: Programming Language :: Python :: 3.9
Requires-Python: >=3.7
License-File: LICENSE.txt
Requires-Dist: click (>=7.1.1)
Requires-Dist: pandas (<1.4,>=1.3.5)
Requires-Dist: pyyaml
Provides-Extra: dev
Requires-Dist: doc8 ; extra == 'dev'
Requires-Dist: flake8 ; extra == 'dev'
Requires-Dist: flake8-docstrings ; extra == 'dev'
Requires-Dist: flake8-tidy-imports ; extra == 'dev'
Requires-Dist: ipython ; extra == 'dev'
Requires-Dist: isort ; extra == 'dev'
Requires-Dist: jupyter ; extra == 'dev'
Requires-Dist: jupyterlab ; extra == 'dev'
Requires-Dist: pandoc ; extra == 'dev'
Requires-Dist: pytest ; extra == 'dev'
Requires-Dist: sphinx ; extra == 'dev'
Requires-Dist: twine ; extra == 'dev'
Requires-Dist: yapf ; extra == 'dev'
